[
  {
    "Table 17": null,
    "Food or Product": null,
    "IMPORTS THAT CAN POTENTIALLY BE PRODUCED DOMESTICALLY ": null,
    "__EMPTY": null,
    "__EMPTY_1": null,
    "__EMPTY_2": "[VT Million]",
    "__EMPTY_3": null,
    "__EMPTY_4": null,
    "__EMPTY_5": null,
    "__EMPTY_6": null,
    "__EMPTY_7": null,
    "__EMPTY_8": null,
    "__EMPTY_9": null,
    "__EMPTY_10": null,
    "__EMPTY_11": null,
    "__EMPTY_12": null,
    "__EMPTY_13": null,
    "__EMPTY_14": null,
    "__EMPTY_15": null,
    "__EMPTY_16": null,
    "__EMPTY_17": null,
    "__EMPTY_18": null,
    "__EMPTY_19": null,
    "__EMPTY_20": null,
    "__EMPTY_21": null,
    "__EMPTY_22": null,
    "__EMPTY_23": null,
    "__EMPTY_24": null,
    "__EMPTY_25": null,
    "__EMPTY_26": null,
    "__EMPTY_27": null,
    "__EMPTY_28": null,
    "__EMPTY_29": null,
    "__EMPTY_30": null,
    "__EMPTY_31": null,
    "__EMPTY_32": null,
    "__EMPTY_33": null,
    "__EMPTY_34": null,
    "__EMPTY_35": null,
    "__EMPTY_36": null,
    "__EMPTY_37": null,
    "__EMPTY_38": null,
    "__EMPTY_39": null,
    "__EMPTY_40": null,
    "__EMPTY_41": null,
    "__EMPTY_42": null,
    "__EMPTY_43": null,
    "__EMPTY_44": null,
    "__EMPTY_45": null,
    "__EMPTY_46": null,
    "__EMPTY_47": null,
    "__EMPTY_48": null,
    "__EMPTY_49": null,
    "__EMPTY_50": null,
    "__EMPTY_51": null,
    "__EMPTY_52": null,
    "__EMPTY_53": null,
    "__EMPTY_54": null,
    "__EMPTY_55": null,
    "__EMPTY_56": null,
    "__EMPTY_57": null,
    "__EMPTY_58": null,
    "__EMPTY_59": null,
    "__EMPTY_60": null,
    "__EMPTY_61": null,
    "__EMPTY_62": null,
    "__EMPTY_63": null,
    "__EMPTY_64": null,
    "__EMPTY_65": null,
    "__EMPTY_66": null,
    "__EMPTY_67": null,
    "__EMPTY_68": null,
    "__EMPTY_69": null,
    "__EMPTY_70": null,
    "__EMPTY_71": null,
    "__EMPTY_72": null,
    "__EMPTY_73": null,
    "__EMPTY_74": null,
    "__EMPTY_75": null,
    "__EMPTY_76": null,
    "__EMPTY_77": null,
    "__EMPTY_78": null,
    "__EMPTY_79": null,
    "__EMPTY_80": null,
    "__EMPTY_81": null,
    "__EMPTY_82": null,
    "__EMPTY_83": null,
    "__EMPTY_84": null,
    "__EMPTY_85": null,
    "__EMPTY_86": null,
    "__EMPTY_87": null,
    "__EMPTY_88": null,
    "__EMPTY_89": null,
    "__EMPTY_90": null,
    "__EMPTY_91": null,
    "__EMPTY_92": null,
    "__EMPTY_93": null,
    "__EMPTY_94": null,
    "__EMPTY_95": null,
    "__EMPTY_96": null,
    "__EMPTY_97": null,
    "__EMPTY_98": null
  },
  {
    "Table 17": null,
    "Food or Product": null,
    "IMPORTS THAT CAN POTENTIALLY BE PRODUCED DOMESTICALLY ": null,
    "__EMPTY": null,
    "__EMPTY_1": null,
    "__EMPTY_2": null,
    "__EMPTY_3": null,
    "__EMPTY_4": null,
    "__EMPTY_5": null,
    "__EMPTY_6": null,
    "__EMPTY_7": null,
    "__EMPTY_8": null,
    "__EMPTY_9": null,
    "__EMPTY_10": null,
    "__EMPTY_11": null,
    "__EMPTY_12": null,
    "__EMPTY_13": null,
    "__EMPTY_14": null,
    "__EMPTY_15": null,
    "__EMPTY_16": null,
    "__EMPTY_17": null,
    "__EMPTY_18": null,
    "__EMPTY_19": null,
    "__EMPTY_20": null,
    "__EMPTY_21": null,
    "__EMPTY_22": null,
    "__EMPTY_23": null,
    "__EMPTY_24": null,
    "__EMPTY_25": null,
    "__EMPTY_26": null,
    "__EMPTY_27": null,
    "__EMPTY_28": null,
    "__EMPTY_29": null,
    "__EMPTY_30": null,
    "__EMPTY_31": null,
    "__EMPTY_32": null,
    "__EMPTY_33": null,
    "__EMPTY_34": null,
    "__EMPTY_35": null,
    "__EMPTY_36": null,
    "__EMPTY_37": null,
    "__EMPTY_38": null,
    "__EMPTY_39": null,
    "__EMPTY_40": null,
    "__EMPTY_41": null,
    "__EMPTY_42": null,
    "__EMPTY_43": null,
    "__EMPTY_44": null,
    "__EMPTY_45": null,
    "__EMPTY_46": null,
    "__EMPTY_47": null,
    "__EMPTY_48": null,
    "__EMPTY_49": null,
    "__EMPTY_50": null,
    "__EMPTY_51": null,
    "__EMPTY_52": null,
    "__EMPTY_53": null,
    "__EMPTY_54": null,
    "__EMPTY_55": null,
    "__EMPTY_56": null,
    "__EMPTY_57": null,
    "__EMPTY_58": null,
    "__EMPTY_59": null,
    "__EMPTY_60": null,
    "__EMPTY_61": null,
    "__EMPTY_62": null,
    "__EMPTY_63": null,
    "__EMPTY_64": null,
    "__EMPTY_65": null,
    "__EMPTY_66": "MONTHLY",
    "__EMPTY_67": null,
    "__EMPTY_68": null,
    "__EMPTY_69": null,
    "__EMPTY_70": null,
    "__EMPTY_71": null,
    "__EMPTY_72": null,
    "__EMPTY_73": null,
    "__EMPTY_74": null,
    "__EMPTY_75": null,
    "__EMPTY_76": null,
    "__EMPTY_77": null,
    "__EMPTY_78": null,
    "__EMPTY_79": null,
    "__EMPTY_80": null,
    "__EMPTY_81": null,
    "__EMPTY_82": null,
    "__EMPTY_83": null,
    "__EMPTY_84": null,
    "__EMPTY_85": null,
    "__EMPTY_86": null,
    "__EMPTY_87": null,
    "__EMPTY_88": null,
    "__EMPTY_89": null,
    "__EMPTY_90": null,
    "__EMPTY_91": null,
    "__EMPTY_92": null,
    "__EMPTY_93": null,
    "__EMPTY_94": null,
    "__EMPTY_95": null,
    "__EMPTY_96": null,
    "__EMPTY_97": null,
    "__EMPTY_98": null
  },
  {
    "Table 17": null,
    "Food or Product": null,
    "IMPORTS THAT CAN POTENTIALLY BE PRODUCED DOMESTICALLY ": "ANNUALLY",
    "__EMPTY": null,
    "__EMPTY_1": null,
    "__EMPTY_2": null,
    "__EMPTY_3": null,
    "__EMPTY_4": null,
    "__EMPTY_5": null,
    "__EMPTY_6": null,
    "__EMPTY_7": null,
    "__EMPTY_8": null,
    "__EMPTY_9": null,
    "__EMPTY_10": null,
    "__EMPTY_11": null,
    "__EMPTY_12": null,
    "__EMPTY_13": null,
    "__EMPTY_14": null,
    "__EMPTY_15": null,
    "__EMPTY_16": null,
    "__EMPTY_17": null,
    "__EMPTY_18": null,
    "__EMPTY_19": null,
    "__EMPTY_20": null,
    "__EMPTY_21": null,
    "__EMPTY_22": null,
    "__EMPTY_23": null,
    "__EMPTY_24": null,
    "__EMPTY_25": null,
    "__EMPTY_26": null,
    "__EMPTY_27": null,
    "__EMPTY_28": null,
    "__EMPTY_29": null,
    "__EMPTY_30": null,
    "__EMPTY_31": null,
    "__EMPTY_32": null,
    "__EMPTY_33": null,
    "__EMPTY_34": null,
    "__EMPTY_35": null,
    "__EMPTY_36": null,
    "__EMPTY_37": null,
    "__EMPTY_38": null,
    "__EMPTY_39": null,
    "__EMPTY_40": null,
    "__EMPTY_41": null,
    "__EMPTY_42": null,
    "__EMPTY_43": 2021,
    "__EMPTY_44": null,
    "__EMPTY_45": null,
    "__EMPTY_46": null,
    "__EMPTY_47": null,
    "__EMPTY_48": null,
    "__EMPTY_49": null,
    "__EMPTY_50": null,
    "__EMPTY_51": null,
    "__EMPTY_52": null,
    "__EMPTY_53": null,
    "__EMPTY_54": null,
    "__EMPTY_55": 2022,
    "__EMPTY_56": null,
    "__EMPTY_57": null,
    "__EMPTY_58": null,
    "__EMPTY_59": null,
    "__EMPTY_60": null,
    "__EMPTY_61": null,
    "__EMPTY_62": null,
    "__EMPTY_63": null,
    "__EMPTY_64": null,
    "__EMPTY_65": null,
    "__EMPTY_66": null,
    "__EMPTY_67": 2023,
    "__EMPTY_68": null,
    "__EMPTY_69": null,
    "__EMPTY_70": null,
    "__EMPTY_71": null,
    "__EMPTY_72": null,
    "__EMPTY_73": null,
    "__EMPTY_74": null,
    "__EMPTY_75": null,
    "__EMPTY_76": null,
    "__EMPTY_77": null,
    "__EMPTY_78": null,
    "__EMPTY_79": 2024,
    "__EMPTY_80": null,
    "__EMPTY_81": null,
    "__EMPTY_82": null,
    "__EMPTY_83": null,
    "__EMPTY_84": null,
    "__EMPTY_85": null,
    "__EMPTY_86": null,
    "__EMPTY_87": null,
    "__EMPTY_88": null,
    "__EMPTY_89": null,
    "__EMPTY_90": null,
    "__EMPTY_91": 2025,
    "__EMPTY_92": null,
    "__EMPTY_93": null,
    "__EMPTY_94": null,
    "__EMPTY_95": null,
    "__EMPTY_96": null,
    "__EMPTY_97": null,
    "__EMPTY_98": null
  },
  {
    "Table 17": null,
    "Food or Product": null,
    "IMPORTS THAT CAN POTENTIALLY BE PRODUCED DOMESTICALLY ": 2018,
    "__EMPTY": 2019,
    "__EMPTY_1": 2020,
    "__EMPTY_2": 2021,
    "__EMPTY_3": 2022,
    "__EMPTY_4": 2023,
    "__EMPTY_5": 2024,
    "__EMPTY_6": "Jan",
    "__EMPTY_7": "Feb",
    "__EMPTY_8": "Mar",
    "__EMPTY_9": "Apr",
    "__EMPTY_10": "May",
    "__EMPTY_11": "Jun",
    "__EMPTY_12": "Jul",
    "__EMPTY_13": "Aug",
    "__EMPTY_14": "Sep",
    "__EMPTY_15": "Oct",
    "__EMPTY_16": "Nov",
    "__EMPTY_17": "Dec",
    "__EMPTY_18": "Jan",
    "__EMPTY_19": "Feb",
    "__EMPTY_20": "Mar",
    "__EMPTY_21": "Apr",
    "__EMPTY_22": "May",
    "__EMPTY_23": "Jun",
    "__EMPTY_24": "Jul",
    "__EMPTY_25": "Aug",
    "__EMPTY_26": "Sep",
    "__EMPTY_27": "Oct",
    "__EMPTY_28": "Nov",
    "__EMPTY_29": "Dec",
    "__EMPTY_30": "Jan",
    "__EMPTY_31": "Feb",
    "__EMPTY_32": "Mar",
    "__EMPTY_33": "Apr",
    "__EMPTY_34": "May",
    "__EMPTY_35": "Jun",
    "__EMPTY_36": "Jul",
    "__EMPTY_37": "Aug",
    "__EMPTY_38": "Sep",
    "__EMPTY_39": "Oct",
    "__EMPTY_40": "Nov",
    "__EMPTY_41": "Dec",
    "__EMPTY_42": "YTD",
    "__EMPTY_43": "Jan",
    "__EMPTY_44": "Feb",
    "__EMPTY_45": "Mar",
    "__EMPTY_46": "Apr",
    "__EMPTY_47": "May",
    "__EMPTY_48": "Jun",
    "__EMPTY_49": "Jul",
    "__EMPTY_50": "Aug",
    "__EMPTY_51": "Sep",
    "__EMPTY_52": "Oct",
    "__EMPTY_53": "Nov",
    "__EMPTY_54": "Dec",
    "__EMPTY_55": "Jan",
    "__EMPTY_56": "Feb",
    "__EMPTY_57": "Mar",
    "__EMPTY_58": "Apr",
    "__EMPTY_59": "May",
    "__EMPTY_60": "Jun",
    "__EMPTY_61": "Jul",
    "__EMPTY_62": "Aug",
    "__EMPTY_63": "Sep",
    "__EMPTY_64": "Oct",
    "__EMPTY_65": "Nov",
    "__EMPTY_66": "Dec",
    "__EMPTY_67": "Jan",
    "__EMPTY_68": "Feb",
    "__EMPTY_69": "Mar",
    "__EMPTY_70": "Apr",
    "__EMPTY_71": "May",
    "__EMPTY_72": "Jun",
    "__EMPTY_73": "Jul",
    "__EMPTY_74": "Aug",
    "__EMPTY_75": "Sep",
    "__EMPTY_76": "Oct",
    "__EMPTY_77": "Nov",
    "__EMPTY_78": "Dec",
    "__EMPTY_79": "Jan",
    "__EMPTY_80": "Feb",
    "__EMPTY_81": "Mar",
    "__EMPTY_82": "Apr",
    "__EMPTY_83": "May",
    "__EMPTY_84": "Jun",
    "__EMPTY_85": "Jul",
    "__EMPTY_86": "Aug",
    "__EMPTY_87": "Sep",
    "__EMPTY_88": "Oct",
    "__EMPTY_89": "Nov",
    "__EMPTY_90": "Dec",
    "__EMPTY_91": "Jan",
    "__EMPTY_92": "Feb",
    "__EMPTY_93": "Mar",
    "__EMPTY_94": "Apr",
    "__EMPTY_95": "May",
    "__EMPTY_96": "Jun",
    "__EMPTY_97": "Jul",
    "__EMPTY_98": null
  },
  {
    "Table 17": null,
    "Food or Product": "Canned Mackerel",
    "IMPORTS THAT CAN POTENTIALLY BE PRODUCED DOMESTICALLY ": 193.403721,
    "__EMPTY": 183.15553099999997,
    "__EMPTY_1": 256.854798,
    "__EMPTY_2": 190.066556,
    "__EMPTY_3": 148.33753699999997,
    "__EMPTY_4": 251.439652,
    "__EMPTY_5": 183.551336,
    "__EMPTY_6": 201.18762800000002,
    "__EMPTY_7": 198.48771700000003,
    "__EMPTY_8": 198.188328,
    "__EMPTY_9": 206.80656400000007,
    "__EMPTY_10": 223.73629800000003,
    "__EMPTY_11": 229.492124,
    "__EMPTY_12": 226.14925200000002,
    "__EMPTY_13": 183.99457299999997,
    "__EMPTY_14": 148.33753699999997,
    "__EMPTY_15": 152.42227199999996,
    "__EMPTY_16": 126.944005,
    "__EMPTY_17": 135.13170200000002,
    "__EMPTY_18": 172.130696,
    "__EMPTY_19": 193.719851,
    "__EMPTY_20": 219.20071800000002,
    "__EMPTY_21": 209.81455499999998,
    "__EMPTY_22": 192.371163,
    "__EMPTY_23": 189.76778000000002,
    "__EMPTY_24": 215.573177,
    "__EMPTY_25": 231.90126899999996,
    "__EMPTY_26": 251.439652,
    "__EMPTY_27": 272.49298899999997,
    "__EMPTY_28": 272.347743,
    "__EMPTY_29": 279.81486899999993,
    "__EMPTY_30": 251.434932,
    "__EMPTY_31": 222.725185,
    "__EMPTY_32": 186.94624599999997,
    "__EMPTY_33": 210.54675500000002,
    "__EMPTY_34": 209.056121,
    "__EMPTY_35": 191.279471,
    "__EMPTY_36": 171.40584700000002,
    "__EMPTY_37": 173.918691,
    "__EMPTY_38": 183.551336,
    "__EMPTY_39": 159.85747999999998,
    "__EMPTY_40": 155.82900099999998,
    "__EMPTY_41": 134.06673099999998,
    "__EMPTY_42": 99.64741900000001,
    "__EMPTY_43": 9.186463,
    "__EMPTY_44": 17.536055,
    "__EMPTY_45": 3.182101,
    "__EMPTY_46": 9.540142,
    "__EMPTY_47": 16.595217,
    "__EMPTY_48": 19.88182,
    "__EMPTY_49": 4.297321,
    "__EMPTY_50": 5.219723,
    "__EMPTY_51": 22.122149,
    "__EMPTY_52": 3.793198,
    "__EMPTY_53": 42.605005,
    "__EMPTY_54": 36.107362,
    "__EMPTY_55": 4.348375,
    "__EMPTY_56": 29.651992,
    "__EMPTY_57": 6.107447,
    "__EMPTY_58": 10.458019,
    "__EMPTY_59": 13.895306,
    "__EMPTY_60": 19.582431,
    "__EMPTY_61": 12.915557,
    "__EMPTY_62": 22.149457,
    "__EMPTY_63": 27.877975,
    "__EMPTY_64": 0.450326,
    "__EMPTY_65": 0.450326,
    "__EMPTY_66": 0.450326,
    "__EMPTY_67": 8.43311,
    "__EMPTY_68": 4.173725,
    "__EMPTY_69": 14.295144,
    "__EMPTY_70": 47.457013,
    "__EMPTY_71": 35.484461,
    "__EMPTY_72": 45.063298,
    "__EMPTY_73": 3.529394,
    "__EMPTY_74": 4.706065,
    "__EMPTY_75": 25.274592,
    "__EMPTY_76": 26.255723,
    "__EMPTY_77": 16.778418,
    "__EMPTY_78": 19.988709,
    "__EMPTY_79": 29.486447,
    "__EMPTY_80": 4.028479,
    "__EMPTY_81": 21.76227,
    "__EMPTY_82": 19.077076,
    "__EMPTY_83": 6.774714,
    "__EMPTY_84": 9.284359,
    "__EMPTY_85": 27.129903,
    "__EMPTY_86": 3.215431,
    "__EMPTY_87": 7.497942,
    "__EMPTY_88": 6.382099,
    "__EMPTY_89": 19.291262,
    "__EMPTY_90": 29.621354,
    "__EMPTY_91": 5.792591,
    "__EMPTY_92": 5.565976,
    "__EMPTY_93": 2.486262,
    "__EMPTY_94": 10.537432,
    "__EMPTY_95": 42.889496,
    "__EMPTY_96": 14.421347,
    "__EMPTY_97": 17.954315,
    "__EMPTY_98": null
  },
  {
    "Table 17": null,
    "Food or Product": "Canned Tunas",
    "IMPORTS THAT CAN POTENTIALLY BE PRODUCED DOMESTICALLY ": 512.1679369999999,
    "__EMPTY": 485.168144,
    "__EMPTY_1": 563.851687,
    "__EMPTY_2": 384.06711299999995,
    "__EMPTY_3": 355.1664960000001,
    "__EMPTY_4": 833.8838570000001,
    "__EMPTY_5": 573.360568,
    "__EMPTY_6": 6.317024,
    "__EMPTY_7": 40.425307,
    "__EMPTY_8": 12.230176,
    "__EMPTY_9": 17.451129,
    "__EMPTY_10": 87.196043,
    "__EMPTY_11": 18.763604,
    "__EMPTY_12": 79.666133,
    "__EMPTY_13": 38.684736,
    "__EMPTY_14": 49.38127,
    "__EMPTY_15": 56.49362,
    "__EMPTY_16": 42.456714,
    "__EMPTY_17": 63.102181,
    "__EMPTY_18": 63.314803,
    "__EMPTY_19": 26.461706,
    "__EMPTY_20": 17.637007,
    "__EMPTY_21": 24.970083,
    "__EMPTY_22": 29.278182,
    "__EMPTY_23": 39.331111,
    "__EMPTY_24": 36.755823,
    "__EMPTY_25": 79.899962,
    "__EMPTY_26": 57.137383,
    "__EMPTY_27": 26.046387,
    "__EMPTY_28": 42.988357,
    "__EMPTY_29": 41.34734,
    "__EMPTY_30": 24.566406,
    "__EMPTY_31": 1.291329,
    "__EMPTY_32": 41.777836,
    "__EMPTY_33": 18.136472,
    "__EMPTY_34": 11.38728,
    "__EMPTY_35": 77.768746,
    "__EMPTY_36": 72.128211,
    "__EMPTY_37": 88.79341,
    "__EMPTY_38": 69.733287,
    "__EMPTY_39": 21.898638,
    "__EMPTY_40": 38.773916,
    "__EMPTY_41": 97.596156,
    "__EMPTY_42": 442.355286,
    "__EMPTY_43": 37.862133,
    "__EMPTY_44": 21.70434,
    "__EMPTY_45": 33.055749,
    "__EMPTY_46": 21.001113,
    "__EMPTY_47": 37.614774,
    "__EMPTY_48": 14.715743,
    "__EMPTY_49": 24.037166,
    "__EMPTY_50": 63.426906,
    "__EMPTY_51": 41.548449,
    "__EMPTY_52": 34.856793,
    "__EMPTY_53": 15.578051,
    "__EMPTY_54": 38.665896,
    "__EMPTY_55": 63.012394,
    "__EMPTY_56": 21.392158,
    "__EMPTY_57": 9.153608,
    "__EMPTY_58": 67.934266,
    "__EMPTY_59": 30.218422,
    "__EMPTY_60": 53.938127,
    "__EMPTY_61": 31.812203,
    "__EMPTY_62": 35.558552,
    "__EMPTY_63": 40.795788,
    "__EMPTY_64": 0.450326,
    "__EMPTY_65": 0.450326,
    "__EMPTY_66": 0.450326,
    "__EMPTY_67": 80.179212,
    "__EMPTY_68": 33.030443,
    "__EMPTY_69": 17.427183,
    "__EMPTY_70": 88.109002,
    "__EMPTY_71": 103.553459,
    "__EMPTY_72": 73.868264,
    "__EMPTY_73": 50.107798,
    "__EMPTY_74": 140.71069,
    "__EMPTY_75": 44.220462,
    "__EMPTY_76": 15.278944,
    "__EMPTY_77": 95.590943,
    "__EMPTY_78": 91.807457,
    "__EMPTY_79": 21.828964,
    "__EMPTY_80": 50.764231,
    "__EMPTY_81": 38.04064,
    "__EMPTY_82": 73.676146,
    "__EMPTY_83": 45.306594,
    "__EMPTY_84": 66.066477,
    "__EMPTY_85": 61.564335,
    "__EMPTY_86": 35.639691,
    "__EMPTY_87": 8.837568,
    "__EMPTY_88": 64.044299,
    "__EMPTY_89": 29.207583,
    "__EMPTY_90": 78.38404,
    "__EMPTY_91": 97.401006,
    "__EMPTY_92": 14.721471,
    "__EMPTY_93": 64.68739,
    "__EMPTY_94": 72.282646,
    "__EMPTY_95": 75.176553,
    "__EMPTY_96": 43.935456,
    "__EMPTY_97": 74.150764,
    "__EMPTY_98": null
  },
  {
    "Table 17": null,
    "Food or Product": "Chicken",
    "IMPORTS THAT CAN POTENTIALLY BE PRODUCED DOMESTICALLY ": 970.594807,
    "__EMPTY": 972.959644,
    "__EMPTY_1": 903.8747939999998,
    "__EMPTY_2": 884.276947,
    "__EMPTY_3": 423.4248140000001,
    "__EMPTY_4": 907.282689,
    "__EMPTY_5": 1160.90382,
    "__EMPTY_6": 61.497154,
    "__EMPTY_7": 45.893012,
    "__EMPTY_8": 82.036274,
    "__EMPTY_9": 56.644245,
    "__EMPTY_10": 76.499036,
    "__EMPTY_11": 84.56057,
    "__EMPTY_12": 94.720754,
    "__EMPTY_13": 81.408435,
    "__EMPTY_14": 119.483703,
    "__EMPTY_15": 97.15093,
    "__EMPTY_16": 102.629444,
    "__EMPTY_17": 68.07125,
    "__EMPTY_18": 54.061848,
    "__EMPTY_19": 54.414275,
    "__EMPTY_20": 86.636118,
    "__EMPTY_21": 105.028252,
    "__EMPTY_22": 63.286762,
    "__EMPTY_23": 61.164615,
    "__EMPTY_24": 91.591901,
    "__EMPTY_25": 62.837497,
    "__EMPTY_26": 82.583285,
    "__EMPTY_27": 78.337031,
    "__EMPTY_28": 78.369005,
    "__EMPTY_29": 154.649055,
    "__EMPTY_30": 36.46149,
    "__EMPTY_31": 79.851084,
    "__EMPTY_32": 102.656261,
    "__EMPTY_33": 93.767245,
    "__EMPTY_34": 45.49818,
    "__EMPTY_35": 86.544156,
    "__EMPTY_36": 81.984361,
    "__EMPTY_37": 55.289402,
    "__EMPTY_38": 79.404736,
    "__EMPTY_39": 46.002587,
    "__EMPTY_40": 59.33039,
    "__EMPTY_41": 137.084902,
    "__EMPTY_42": 570.369983,
    "__EMPTY_43": 66.584252,
    "__EMPTY_44": 72.746789,
    "__EMPTY_45": 41.213187,
    "__EMPTY_46": 60.276353,
    "__EMPTY_47": 68.940719,
    "__EMPTY_48": 106.476513,
    "__EMPTY_49": 40.67619,
    "__EMPTY_50": 67.720206,
    "__EMPTY_51": 78.061734,
    "__EMPTY_52": 23.563553,
    "__EMPTY_53": 109.497263,
    "__EMPTY_54": 148.520188,
    "__EMPTY_55": 36.67929,
    "__EMPTY_56": 78.622289,
    "__EMPTY_57": 49.915872,
    "__EMPTY_58": 12.860592,
    "__EMPTY_59": 35.307194,
    "__EMPTY_60": 42.397457,
    "__EMPTY_61": 90.131088,
    "__EMPTY_62": 17.034924,
    "__EMPTY_63": 59.12513,
    "__EMPTY_64": 0.450326,
    "__EMPTY_65": 0.450326,
    "__EMPTY_66": 0.450326,
    "__EMPTY_67": 48.29778,
    "__EMPTY_68": 56.224962,
    "__EMPTY_69": 46.703395,
    "__EMPTY_70": 17.315296,
    "__EMPTY_71": 49.335397,
    "__EMPTY_72": 53.204863,
    "__EMPTY_73": 50.23642,
    "__EMPTY_74": 134.643627,
    "__EMPTY_75": 147.731707,
    "__EMPTY_76": 80.8226,
    "__EMPTY_77": 52.722574,
    "__EMPTY_78": 170.044068,
    "__EMPTY_79": 206.568801,
    "__EMPTY_80": 98.518777,
    "__EMPTY_81": 61.818144,
    "__EMPTY_82": 53.512655,
    "__EMPTY_83": 52.797594,
    "__EMPTY_84": 72.693496,
    "__EMPTY_85": 66.18277,
    "__EMPTY_86": 36.731275,
    "__EMPTY_87": 15.496173,
    "__EMPTY_88": 133.184087,
    "__EMPTY_89": 122.179093,
    "__EMPTY_90": 241.220955,
    "__EMPTY_91": 72.126323,
    "__EMPTY_92": 80.671594,
    "__EMPTY_93": 50.941771,
    "__EMPTY_94": 116.29062,
    "__EMPTY_95": 43.680089,
    "__EMPTY_96": 73.05239,
    "__EMPTY_97": 133.607196,
    "__EMPTY_98": null
  },
  {
    "Table 17": null,
    "Food or Product": "Chicken Eggs",
    "IMPORTS THAT CAN POTENTIALLY BE PRODUCED DOMESTICALLY ": 77.61769799999999,
    "__EMPTY": 58.06671299999999,
    "__EMPTY_1": 24.146485000000002,
    "__EMPTY_2": 36.594833,
    "__EMPTY_3": 14.372897,
    "__EMPTY_4": 121.21292600000001,
    "__EMPTY_5": 177.767369,
    "__EMPTY_6": 4.221685,
    "__EMPTY_7": 2.11129,
    "__EMPTY_8": 3.026882,
    "__EMPTY_9": 4.329704,
    "__EMPTY_10": 4.031274,
    "__EMPTY_11": 4.995166,
    "__EMPTY_12": 12.105699,
    "__EMPTY_13": 7.476453,
    "__EMPTY_14": 11.504753,
    "__EMPTY_15": 7.546852,
    "__EMPTY_16": 8.410065,
    "__EMPTY_17": 7.857875,
    "__EMPTY_18": 3.300144,
    "__EMPTY_19": 3.483908,
    "__EMPTY_20": 2.549404,
    "__EMPTY_21": 6.784247,
    "__EMPTY_22": 5.614298,
    "__EMPTY_23": 2.244234,
    "__EMPTY_24": 5.902709,
    "__EMPTY_25": 2.989772,
    "__EMPTY_26": 1.62085,
    "__EMPTY_27": 9.186101,
    "__EMPTY_28": 7.060472,
    "__EMPTY_29": 7.330574,
    "__EMPTY_30": 2.207924,
    "__EMPTY_31": 2.727869,
    "__EMPTY_32": 2.279385,
    "__EMPTY_33": 0.691482,
    "__EMPTY_34": 0.750978,
    "__EMPTY_35": 1.606125,
    "__EMPTY_36": 1.558485,
    "__EMPTY_37": 0.878206,
    "__EMPTY_38": 1.382319,
    "__EMPTY_39": 1.866153,
    "__EMPTY_40": 2.087402,
    "__EMPTY_41": 6.110157,
    "__EMPTY_42": 91.362099,
    "__EMPTY_43": 2.11864,
    "__EMPTY_44": 1.374491,
    "__EMPTY_45": 0.456342,
    "__EMPTY_46": 1.539916,
    "__EMPTY_47": 4.503674,
    "__EMPTY_48": 1.033416,
    "__EMPTY_49": 0.918386,
    "__EMPTY_50": 6.403975,
    "__EMPTY_51": 8.217181,
    "__EMPTY_52": 0.450326,
    "__EMPTY_53": 1.546602,
    "__EMPTY_54": 8.031884,
    "__EMPTY_55": 0,
    "__EMPTY_56": 0,
    "__EMPTY_57": 5.632334,
    "__EMPTY_58": 0,
    "__EMPTY_59": 1.305926,
    "__EMPTY_60": 0,
    "__EMPTY_61": 2.954251,
    "__EMPTY_62": 0.747415,
    "__EMPTY_63": 2.381993,
    "__EMPTY_64": 0.450326,
    "__EMPTY_65": 0.450326,
    "__EMPTY_66": 0.450326,
    "__EMPTY_67": 5.979686,
    "__EMPTY_68": 0,
    "__EMPTY_69": 2.61372,
    "__EMPTY_70": 3.123575,
    "__EMPTY_71": 0.927053,
    "__EMPTY_72": 0,
    "__EMPTY_73": 22.630679,
    "__EMPTY_74": 15.95292,
    "__EMPTY_75": 17.207847,
    "__EMPTY_76": 18.812556,
    "__EMPTY_77": 11.2487,
    "__EMPTY_78": 22.71619,
    "__EMPTY_79": 28.288355,
    "__EMPTY_80": 17.897751,
    "__EMPTY_81": 11.560144,
    "__EMPTY_82": 19.261824,
    "__EMPTY_83": 14.052468,
    "__EMPTY_84": 3.708158,
    "__EMPTY_85": 14.582041,
    "__EMPTY_86": 7.176148,
    "__EMPTY_87": 7.961126,
    "__EMPTY_88": 18.002608,
    "__EMPTY_89": 18.297977,
    "__EMPTY_90": 16.978769,
    "__EMPTY_91": null,
    "__EMPTY_92": 10.738034,
    "__EMPTY_93": 0.666629,
    "__EMPTY_94": 32.85994,
    "__EMPTY_95": 9.138877,
    "__EMPTY_96": 11.145944,
    "__EMPTY_97": 26.812675,
    "__EMPTY_98": null
  },
  {
    "Table 17": null,
    "Food or Product": "TOTAL",
    "IMPORTS THAT CAN POTENTIALLY BE PRODUCED DOMESTICALLY ": 1753.7841629999998,
    "__EMPTY": 1699.350032,
    "__EMPTY_1": 1748.727764,
    "__EMPTY_2": 1495.005449,
    "__EMPTY_3": 941.3017440000001,
    "__EMPTY_4": 2113.819124,
    "__EMPTY_5": 2095.583093,
    "__EMPTY_6": 273.223491,
    "__EMPTY_7": 286.91732600000006,
    "__EMPTY_8": 295.48166000000003,
    "__EMPTY_9": 285.2316420000001,
    "__EMPTY_10": 391.46265100000005,
    "__EMPTY_11": 337.81146399999994,
    "__EMPTY_12": 412.641838,
    "__EMPTY_13": 311.564197,
    "__EMPTY_14": 328.70726299999995,
    "__EMPTY_15": 313.61367399999995,
    "__EMPTY_16": 280.440228,
    "__EMPTY_17": 274.163008,
    "__EMPTY_18": 292.80749099999997,
    "__EMPTY_19": 278.07973999999996,
    "__EMPTY_20": 326.023247,
    "__EMPTY_21": 346.597137,
    "__EMPTY_22": 290.550405,
    "__EMPTY_23": 292.50774,
    "__EMPTY_24": 349.82361,
    "__EMPTY_25": 377.6285,
    "__EMPTY_26": 392.78117000000003,
    "__EMPTY_27": 386.062508,
    "__EMPTY_28": 400.765577,
    "__EMPTY_29": 483.14183799999995,
    "__EMPTY_30": 314.67075200000005,
    "__EMPTY_31": 306.595467,
    "__EMPTY_32": 333.659728,
    "__EMPTY_33": 323.141954,
    "__EMPTY_34": 266.69255899999996,
    "__EMPTY_35": 357.19849800000003,
    "__EMPTY_36": 327.076904,
    "__EMPTY_37": 318.87970899999993,
    "__EMPTY_38": 334.071678,
    "__EMPTY_39": 229.624858,
    "__EMPTY_40": 256.020709,
    "__EMPTY_41": 374.85794599999997,
    "__EMPTY_42": 1203.734787,
    "__EMPTY_43": 115.75148800000001,
    "__EMPTY_44": 113.36167500000002,
    "__EMPTY_45": 77.907379,
    "__EMPTY_46": 92.35752400000001,
    "__EMPTY_47": 127.65438400000001,
    "__EMPTY_48": 142.10749199999998,
    "__EMPTY_49": 69.929063,
    "__EMPTY_50": 142.77081,
    "__EMPTY_51": 149.949513,
    "__EMPTY_52": 62.663869999999996,
    "__EMPTY_53": 169.226921,
    "__EMPTY_54": 231.32532999999998,
    "__EMPTY_55": 104.04005900000001,
    "__EMPTY_56": 129.666439,
    "__EMPTY_57": 70.809261,
    "__EMPTY_58": 91.25287699999998,
    "__EMPTY_59": 80.726848,
    "__EMPTY_60": 115.918015,
    "__EMPTY_61": 137.81309900000002,
    "__EMPTY_62": 75.49034800000001,
    "__EMPTY_63": 130.18088600000002,
    "__EMPTY_64": 0.450326,
    "__EMPTY_65": 0.450326,
    "__EMPTY_66": 0.450326,
    "__EMPTY_67": 142.88978799999998,
    "__EMPTY_68": 93.42912999999999,
    "__EMPTY_69": 81.03944200000001,
    "__EMPTY_70": 156.00488599999997,
    "__EMPTY_71": 189.30037000000002,
    "__EMPTY_72": 172.136425,
    "__EMPTY_73": 126.50429100000001,
    "__EMPTY_74": 296.013302,
    "__EMPTY_75": 234.43460800000003,
    "__EMPTY_76": 141.169823,
    "__EMPTY_77": 176.34063500000002,
    "__EMPTY_78": 304.556424,
    "__EMPTY_79": 286.172567,
    "__EMPTY_80": 171.209238,
    "__EMPTY_81": 133.181198,
    "__EMPTY_82": 165.527701,
    "__EMPTY_83": 118.93137,
    "__EMPTY_84": 151.75249,
    "__EMPTY_85": 169.459049,
    "__EMPTY_86": 82.762545,
    "__EMPTY_87": 39.792809,
    "__EMPTY_88": 221.613093,
    "__EMPTY_89": 188.975915,
    "__EMPTY_90": 366.205118,
    "__EMPTY_91": 175.31992,
    "__EMPTY_92": 111.697075,
    "__EMPTY_93": 118.782052,
    "__EMPTY_94": 231.970638,
    "__EMPTY_95": 170.885015,
    "__EMPTY_96": 142.555137,
    "__EMPTY_97": 252.52495,
    "__EMPTY_98": null
  },
  {
    "Table 17": "Notes:",
    "Food or Product": "Classification used: HS17 from January 2017.  Prior to that HS12.",
    "IMPORTS THAT CAN POTENTIALLY BE PRODUCED DOMESTICALLY ": null,
    "__EMPTY": null,
    "__EMPTY_1": null,
    "__EMPTY_2": null,
    "__EMPTY_3": null,
    "__EMPTY_4": null,
    "__EMPTY_5": null,
    "__EMPTY_6": null,
    "__EMPTY_7": null,
    "__EMPTY_8": null,
    "__EMPTY_9": null,
    "__EMPTY_10": null,
    "__EMPTY_11": null,
    "__EMPTY_12": null,
    "__EMPTY_13": null,
    "__EMPTY_14": null,
    "__EMPTY_15": null,
    "__EMPTY_16": null,
    "__EMPTY_17": null,
    "__EMPTY_18": null,
    "__EMPTY_19": null,
    "__EMPTY_20": null,
    "__EMPTY_21": null,
    "__EMPTY_22": null,
    "__EMPTY_23": null,
    "__EMPTY_24": null,
    "__EMPTY_25": null,
    "__EMPTY_26": null,
    "__EMPTY_27": null,
    "__EMPTY_28": null,
    "__EMPTY_29": null,
    "__EMPTY_30": null,
    "__EMPTY_31": null,
    "__EMPTY_32": null,
    "__EMPTY_33": null,
    "__EMPTY_34": null,
    "__EMPTY_35": null,
    "__EMPTY_36": null,
    "__EMPTY_37": null,
    "__EMPTY_38": null,
    "__EMPTY_39": null,
    "__EMPTY_40": null,
    "__EMPTY_41": null,
    "__EMPTY_42": null,
    "__EMPTY_43": null,
    "__EMPTY_44": null,
    "__EMPTY_45": null,
    "__EMPTY_46": null,
    "__EMPTY_47": null,
    "__EMPTY_48": null,
    "__EMPTY_49": null,
    "__EMPTY_50": null,
    "__EMPTY_51": null,
    "__EMPTY_52": null,
    "__EMPTY_53": null,
    "__EMPTY_54": null,
    "__EMPTY_55": null,
    "__EMPTY_56": null,
    "__EMPTY_57": null,
    "__EMPTY_58": null,
    "__EMPTY_59": null,
    "__EMPTY_60": null,
    "__EMPTY_61": null,
    "__EMPTY_62": null,
    "__EMPTY_63": null,
    "__EMPTY_64": null,
    "__EMPTY_65": null,
    "__EMPTY_66": null,
    "__EMPTY_67": null,
    "__EMPTY_68": null,
    "__EMPTY_69": null,
    "__EMPTY_70": null,
    "__EMPTY_71": null,
    "__EMPTY_72": null,
    "__EMPTY_73": null,
    "__EMPTY_74": null,
    "__EMPTY_75": null,
    "__EMPTY_76": null,
    "__EMPTY_77": null,
    "__EMPTY_78": null,
    "__EMPTY_79": null,
    "__EMPTY_80": null,
    "__EMPTY_81": null,
    "__EMPTY_82": null,
    "__EMPTY_83": null,
    "__EMPTY_84": null,
    "__EMPTY_85": null,
    "__EMPTY_86": null,
    "__EMPTY_87": null,
    "__EMPTY_88": null,
    "__EMPTY_89": null,
    "__EMPTY_90": null,
    "__EMPTY_91": null,
    "__EMPTY_92": null,
    "__EMPTY_93": null,
    "__EMPTY_94": null,
    "__EMPTY_95": null,
    "__EMPTY_96": null,
    "__EMPTY_97": null,
    "__EMPTY_98": null
  },
  {
    "Table 17": null,
    "Food or Product": "Data source: Customs and Enterprises",
    "IMPORTS THAT CAN POTENTIALLY BE PRODUCED DOMESTICALLY ": null,
    "__EMPTY": null,
    "__EMPTY_1": null,
    "__EMPTY_2": null,
    "__EMPTY_3": null,
    "__EMPTY_4": null,
    "__EMPTY_5": null,
    "__EMPTY_6": null,
    "__EMPTY_7": null,
    "__EMPTY_8": null,
    "__EMPTY_9": null,
    "__EMPTY_10": null,
    "__EMPTY_11": null,
    "__EMPTY_12": null,
    "__EMPTY_13": null,
    "__EMPTY_14": null,
    "__EMPTY_15": null,
    "__EMPTY_16": null,
    "__EMPTY_17": null,
    "__EMPTY_18": null,
    "__EMPTY_19": null,
    "__EMPTY_20": null,
    "__EMPTY_21": null,
    "__EMPTY_22": null,
    "__EMPTY_23": null,
    "__EMPTY_24": null,
    "__EMPTY_25": null,
    "__EMPTY_26": null,
    "__EMPTY_27": null,
    "__EMPTY_28": null,
    "__EMPTY_29": null,
    "__EMPTY_30": null,
    "__EMPTY_31": null,
    "__EMPTY_32": null,
    "__EMPTY_33": null,
    "__EMPTY_34": null,
    "__EMPTY_35": null,
    "__EMPTY_36": null,
    "__EMPTY_37": null,
    "__EMPTY_38": null,
    "__EMPTY_39": null,
    "__EMPTY_40": null,
    "__EMPTY_41": null,
    "__EMPTY_42": null,
    "__EMPTY_43": null,
    "__EMPTY_44": null,
    "__EMPTY_45": null,
    "__EMPTY_46": null,
    "__EMPTY_47": null,
    "__EMPTY_48": null,
    "__EMPTY_49": null,
    "__EMPTY_50": null,
    "__EMPTY_51": null,
    "__EMPTY_52": null,
    "__EMPTY_53": null,
    "__EMPTY_54": null,
    "__EMPTY_55": null,
    "__EMPTY_56": null,
    "__EMPTY_57": null,
    "__EMPTY_58": null,
    "__EMPTY_59": null,
    "__EMPTY_60": null,
    "__EMPTY_61": null,
    "__EMPTY_62": null,
    "__EMPTY_63": null,
    "__EMPTY_64": null,
    "__EMPTY_65": null,
    "__EMPTY_66": null,
    "__EMPTY_67": null,
    "__EMPTY_68": null,
    "__EMPTY_69": null,
    "__EMPTY_70": null,
    "__EMPTY_71": null,
    "__EMPTY_72": null,
    "__EMPTY_73": null,
    "__EMPTY_74": null,
    "__EMPTY_75": null,
    "__EMPTY_76": null,
    "__EMPTY_77": null,
    "__EMPTY_78": null,
    "__EMPTY_79": null,
    "__EMPTY_80": null,
    "__EMPTY_81": null,
    "__EMPTY_82": null,
    "__EMPTY_83": null,
    "__EMPTY_84": null,
    "__EMPTY_85": null,
    "__EMPTY_86": null,
    "__EMPTY_87": null,
    "__EMPTY_88": null,
    "__EMPTY_89": null,
    "__EMPTY_90": null,
    "__EMPTY_91": null,
    "__EMPTY_92": null,
    "__EMPTY_93": null,
    "__EMPTY_94": null,
    "__EMPTY_95": null,
    "__EMPTY_96": null,
    "__EMPTY_97": null,
    "__EMPTY_98": null
  },
  {
    "Table 17": null,
    "Food or Product": "From 2018 to date",
    "IMPORTS THAT CAN POTENTIALLY BE PRODUCED DOMESTICALLY ": null,
    "__EMPTY": null,
    "__EMPTY_1": null,
    "__EMPTY_2": null,
    "__EMPTY_3": null,
    "__EMPTY_4": null,
    "__EMPTY_5": null,
    "__EMPTY_6": null,
    "__EMPTY_7": null,
    "__EMPTY_8": null,
    "__EMPTY_9": null,
    "__EMPTY_10": null,
    "__EMPTY_11": null,
    "__EMPTY_12": null,
    "__EMPTY_13": null,
    "__EMPTY_14": null,
    "__EMPTY_15": null,
    "__EMPTY_16": null,
    "__EMPTY_17": null,
    "__EMPTY_18": null,
    "__EMPTY_19": null,
    "__EMPTY_20": null,
    "__EMPTY_21": null,
    "__EMPTY_22": null,
    "__EMPTY_23": null,
    "__EMPTY_24": null,
    "__EMPTY_25": null,
    "__EMPTY_26": null,
    "__EMPTY_27": null,
    "__EMPTY_28": null,
    "__EMPTY_29": null,
    "__EMPTY_30": null,
    "__EMPTY_31": null,
    "__EMPTY_32": null,
    "__EMPTY_33": null,
    "__EMPTY_34": null,
    "__EMPTY_35": null,
    "__EMPTY_36": null,
    "__EMPTY_37": null,
    "__EMPTY_38": null,
    "__EMPTY_39": null,
    "__EMPTY_40": null,
    "__EMPTY_41": null,
    "__EMPTY_42": null,
    "__EMPTY_43": null,
    "__EMPTY_44": null,
    "__EMPTY_45": null,
    "__EMPTY_46": null,
    "__EMPTY_47": null,
    "__EMPTY_48": null,
    "__EMPTY_49": null,
    "__EMPTY_50": null,
    "__EMPTY_51": null,
    "__EMPTY_52": null,
    "__EMPTY_53": null,
    "__EMPTY_54": null,
    "__EMPTY_55": null,
    "__EMPTY_56": null,
    "__EMPTY_57": null,
    "__EMPTY_58": null,
    "__EMPTY_59": null,
    "__EMPTY_60": null,
    "__EMPTY_61": null,
    "__EMPTY_62": null,
    "__EMPTY_63": null,
    "__EMPTY_64": null,
    "__EMPTY_65": null,
    "__EMPTY_66": null,
    "__EMPTY_67": null,
    "__EMPTY_68": null,
    "__EMPTY_69": null,
    "__EMPTY_70": null,
    "__EMPTY_71": null,
    "__EMPTY_72": null,
    "__EMPTY_73": null,
    "__EMPTY_74": null,
    "__EMPTY_75": null,
    "__EMPTY_76": null,
    "__EMPTY_77": null,
    "__EMPTY_78": null,
    "__EMPTY_79": null,
    "__EMPTY_80": null,
    "__EMPTY_81": null,
    "__EMPTY_82": null,
    "__EMPTY_83": null,
    "__EMPTY_84": null,
    "__EMPTY_85": null,
    "__EMPTY_86": null,
    "__EMPTY_87": null,
    "__EMPTY_88": null,
    "__EMPTY_89": null,
    "__EMPTY_90": null,
    "__EMPTY_91": null,
    "__EMPTY_92": null,
    "__EMPTY_93": null,
    "__EMPTY_94": null,
    "__EMPTY_95": null,
    "__EMPTY_96": null,
    "__EMPTY_97": null,
    "__EMPTY_98": null
  },
  {
    "Table 17": null,
    "Food or Product": "NB: 2021 -2024 revised due to change in import classification",
    "IMPORTS THAT CAN POTENTIALLY BE PRODUCED DOMESTICALLY ": null,
    "__EMPTY": null,
    "__EMPTY_1": null,
    "__EMPTY_2": null,
    "__EMPTY_3": null,
    "__EMPTY_4": null,
    "__EMPTY_5": null,
    "__EMPTY_6": null,
    "__EMPTY_7": null,
    "__EMPTY_8": null,
    "__EMPTY_9": null,
    "__EMPTY_10": null,
    "__EMPTY_11": null,
    "__EMPTY_12": null,
    "__EMPTY_13": null,
    "__EMPTY_14": null,
    "__EMPTY_15": null,
    "__EMPTY_16": null,
    "__EMPTY_17": null,
    "__EMPTY_18": null,
    "__EMPTY_19": null,
    "__EMPTY_20": null,
    "__EMPTY_21": null,
    "__EMPTY_22": null,
    "__EMPTY_23": null,
    "__EMPTY_24": null,
    "__EMPTY_25": null,
    "__EMPTY_26": null,
    "__EMPTY_27": null,
    "__EMPTY_28": null,
    "__EMPTY_29": null,
    "__EMPTY_30": null,
    "__EMPTY_31": null,
    "__EMPTY_32": null,
    "__EMPTY_33": null,
    "__EMPTY_34": null,
    "__EMPTY_35": null,
    "__EMPTY_36": null,
    "__EMPTY_37": null,
    "__EMPTY_38": null,
    "__EMPTY_39": null,
    "__EMPTY_40": null,
    "__EMPTY_41": null,
    "__EMPTY_42": null,
    "__EMPTY_43": null,
    "__EMPTY_44": null,
    "__EMPTY_45": null,
    "__EMPTY_46": null,
    "__EMPTY_47": null,
    "__EMPTY_48": null,
    "__EMPTY_49": null,
    "__EMPTY_50": null,
    "__EMPTY_51": null,
    "__EMPTY_52": null,
    "__EMPTY_53": null,
    "__EMPTY_54": null,
    "__EMPTY_55": null,
    "__EMPTY_56": null,
    "__EMPTY_57": null,
    "__EMPTY_58": null,
    "__EMPTY_59": null,
    "__EMPTY_60": null,
    "__EMPTY_61": null,
    "__EMPTY_62": null,
    "__EMPTY_63": null,
    "__EMPTY_64": null,
    "__EMPTY_65": null,
    "__EMPTY_66": null,
    "__EMPTY_67": null,
    "__EMPTY_68": null,
    "__EMPTY_69": null,
    "__EMPTY_70": null,
    "__EMPTY_71": null,
    "__EMPTY_72": null,
    "__EMPTY_73": null,
    "__EMPTY_74": null,
    "__EMPTY_75": null,
    "__EMPTY_76": null,
    "__EMPTY_77": null,
    "__EMPTY_78": null,
    "__EMPTY_79": null,
    "__EMPTY_80": null,
    "__EMPTY_81": null,
    "__EMPTY_82": null,
    "__EMPTY_83": null,
    "__EMPTY_84": null,
    "__EMPTY_85": null,
    "__EMPTY_86": null,
    "__EMPTY_87": null,
    "__EMPTY_88": null,
    "__EMPTY_89": null,
    "__EMPTY_90": null,
    "__EMPTY_91": null,
    "__EMPTY_92": null,
    "__EMPTY_93": null,
    "__EMPTY_94": null,
    "__EMPTY_95": null,
    "__EMPTY_96": null,
    "__EMPTY_97": null,
    "__EMPTY_98": null
  },
  {
    "Table 17": null,
    "Food or Product": null,
    "IMPORTS THAT CAN POTENTIALLY BE PRODUCED DOMESTICALLY ": null,
    "__EMPTY": null,
    "__EMPTY_1": null,
    "__EMPTY_2": null,
    "__EMPTY_3": null,
    "__EMPTY_4": null,
    "__EMPTY_5": null,
    "__EMPTY_6": null,
    "__EMPTY_7": null,
    "__EMPTY_8": null,
    "__EMPTY_9": null,
    "__EMPTY_10": null,
    "__EMPTY_11": null,
    "__EMPTY_12": null,
    "__EMPTY_13": null,
    "__EMPTY_14": null,
    "__EMPTY_15": null,
    "__EMPTY_16": "`",
    "__EMPTY_17": null,
    "__EMPTY_18": null,
    "__EMPTY_19": null,
    "__EMPTY_20": null,
    "__EMPTY_21": null,
    "__EMPTY_22": null,
    "__EMPTY_23": null,
    "__EMPTY_24": null,
    "__EMPTY_25": null,
    "__EMPTY_26": null,
    "__EMPTY_27": null,
    "__EMPTY_28": null,
    "__EMPTY_29": null,
    "__EMPTY_30": null,
    "__EMPTY_31": null,
    "__EMPTY_32": null,
    "__EMPTY_33": null,
    "__EMPTY_34": null,
    "__EMPTY_35": null,
    "__EMPTY_36": null,
    "__EMPTY_37": null,
    "__EMPTY_38": null,
    "__EMPTY_39": null,
    "__EMPTY_40": null,
    "__EMPTY_41": null,
    "__EMPTY_42": null,
    "__EMPTY_43": null,
    "__EMPTY_44": null,
    "__EMPTY_45": null,
    "__EMPTY_46": null,
    "__EMPTY_47": null,
    "__EMPTY_48": null,
    "__EMPTY_49": null,
    "__EMPTY_50": null,
    "__EMPTY_51": null,
    "__EMPTY_52": null,
    "__EMPTY_53": null,
    "__EMPTY_54": null,
    "__EMPTY_55": null,
    "__EMPTY_56": null,
    "__EMPTY_57": null,
    "__EMPTY_58": null,
    "__EMPTY_59": null,
    "__EMPTY_60": null,
    "__EMPTY_61": null,
    "__EMPTY_62": null,
    "__EMPTY_63": null,
    "__EMPTY_64": null,
    "__EMPTY_65": null,
    "__EMPTY_66": null,
    "__EMPTY_67": null,
    "__EMPTY_68": null,
    "__EMPTY_69": null,
    "__EMPTY_70": null,
    "__EMPTY_71": null,
    "__EMPTY_72": null,
    "__EMPTY_73": null,
    "__EMPTY_74": null,
    "__EMPTY_75": null,
    "__EMPTY_76": null,
    "__EMPTY_77": null,
    "__EMPTY_78": null,
    "__EMPTY_79": null,
    "__EMPTY_80": null,
    "__EMPTY_81": null,
    "__EMPTY_82": null,
    "__EMPTY_83": null,
    "__EMPTY_84": null,
    "__EMPTY_85": null,
    "__EMPTY_86": null,
    "__EMPTY_87": null,
    "__EMPTY_88": null,
    "__EMPTY_89": null,
    "__EMPTY_90": null,
    "__EMPTY_91": null,
    "__EMPTY_92": null,
    "__EMPTY_93": null,
    "__EMPTY_94": null,
    "__EMPTY_95": null,
    "__EMPTY_96": null,
    "__EMPTY_97": null,
    "__EMPTY_98": null
  }
]